{"number_of_cuts": 3, "elapsed_time": 49.73, "number_of_partitions_checked": 714, "sel_partitions": [{"partition": [46, 71, 88], "ligation_fidelity": 0.99, "fragment_length_unevenness": 2.833, "cost": 810.0, "fusion_sites": ["AGCA", "ACAC", "ATAG"], "fragments": ["VYKACPKMFATQVMRTHPAWIGKPLCLGPAVCGPCYDQQKHIWMVS", "IDAHCKQCGRCDKPWIEKVYTYQRH", "LNLTDVLCYDSAPYAHN", "IGMISWYWNKVI"], "expression": "\n[VYKACPKMFATQVMRTHPAWIGKPLCLGPAVCGPCYDQQKHIWMV]<AGC|A>\n                                               <AGC|A>TA[DAHCKQCGRCDKPWIEKVYTYQ]AG<ACAC|>\n                                                                                  <ACAC|>[LNLTDVLCYDSAPYAHN]<|ATAG>\n                                                                                                            <|ATAG>GG[MISWYWNKVI]", "fragment_with_fusion_sites": {"VYKACPKMFATQVMRTHPAWIGKPLCLGPAVCGPCYDQQKHIWMVS": {"order": 0, "c_term_dna": "<AGC|A>", "middle_aa": "VYKACPKMFATQVMRTHPAWIGKPLCLGPAVCGPCYDQQKHIWMV"}, "IDAHCKQCGRCDKPWIEKVYTYQRH": {"order": 1, "n_term_dna": "<AGC|A>TA", "middle_aa": "DAHCKQCGRCDKPWIEKVYTYQ", "c_term_dna": "AG<ACAC|>"}, "LNLTDVLCYDSAPYAHN": {"order": 2, "n_term_dna": "<ACAC|>", "middle_aa": "LNLTDVLCYDSAPYAHN", "c_term_dna": "<|ATAG>"}, "IGMISWYWNKVI": {"order": 3, "n_term_dna": "<|ATAG>GG", "middle_aa": "MISWYWNKVI"}}}, {"partition": [46, 72, 88], "ligation_fidelity": 0.99, "fragment_length_unevenness": 2.833, "cost": 810.0, "fusion_sites": ["AGCA", "CAAC", "ATAG"], "fragments": ["VYKACPKMFATQVMRTHPAWIGKPLCLGPAVCGPCYDQQKHIWMVS", "IDAHCKQCGRCDKPWIEKVYTYQRHL", "NLTDVLCYDSAPYAHN", "IGMISWYWNKVI"], "expression": "\n[VYKACPKMFATQVMRTHPAWIGKPLCLGPAVCGPCYDQQKHIWMV]<AGC|A>\n                                               <AGC|A>TA[DAHCKQCGRCDKPWIEKVYTYQRH]CT<C|AAC>\n                                                                                    <C|AAC>[LTDVLCYDSAPYAHN]<|ATAG>\n                                                                                                            <|ATAG>GG[MISWYWNKVI]", "fragment_with_fusion_sites": {"VYKACPKMFATQVMRTHPAWIGKPLCLGPAVCGPCYDQQKHIWMVS": {"order": 0, "c_term_dna": "<AGC|A>", "middle_aa": "VYKACPKMFATQVMRTHPAWIGKPLCLGPAVCGPCYDQQKHIWMV"}, "IDAHCKQCGRCDKPWIEKVYTYQRHL": {"order": 1, "n_term_dna": "<AGC|A>TA", "middle_aa": "DAHCKQCGRCDKPWIEKVYTYQRH", "c_term_dna": "CT<C|AAC>"}, "NLTDVLCYDSAPYAHN": {"order": 2, "n_term_dna": "<C|AAC>", "middle_aa": "LTDVLCYDSAPYAHN", "c_term_dna": "<|ATAG>"}, "IGMISWYWNKVI": {"order": 3, "n_term_dna": "<|ATAG>GG", "middle_aa": "MISWYWNKVI"}}}, {"partition": [46, 73, 88], "ligation_fidelity": 0.99, "fragment_length_unevenness": 2.833, "cost": 810.0, "fusion_sites": ["AGCA", "ACCT", "ATAG"], "fragments": ["VYKACPKMFATQVMRTHPAWIGKPLCLGPAVCGPCYDQQKHIWMVS", "IDAHCKQCGRCDKPWIEKVYTYQRHLN", "LTDVLCYDSAPYAHN", "IGMISWYWNKVI"], "expression": "\n[VYKACPKMFATQVMRTHPAWIGKPLCLGPAVCGPCYDQQKHIWMV]<AGC|A>\n                                               <AGC|A>TA[DAHCKQCGRCDKPWIEKVYTYQRHL]A<AC|CT>\n                                                                                    <AC|CT>G[TDVLCYDSAPYAHN]<|ATAG>\n                                                                                                            <|ATAG>GG[MISWYWNKVI]", "fragment_with_fusion_sites": {"VYKACPKMFATQVMRTHPAWIGKPLCLGPAVCGPCYDQQKHIWMVS": {"order": 0, "c_term_dna": "<AGC|A>", "middle_aa": "VYKACPKMFATQVMRTHPAWIGKPLCLGPAVCGPCYDQQKHIWMV"}, "IDAHCKQCGRCDKPWIEKVYTYQRHLN": {"order": 1, "n_term_dna": "<AGC|A>TA", "middle_aa": "DAHCKQCGRCDKPWIEKVYTYQRHL", "c_term_dna": "A<AC|CT>"}, "LTDVLCYDSAPYAHN": {"order": 2, "n_term_dna": "<AC|CT>G", "middle_aa": "TDVLCYDSAPYAHN", "c_term_dna": "<|ATAG>"}, "IGMISWYWNKVI": {"order": 3, "n_term_dna": "<|ATAG>GG", "middle_aa": "MISWYWNKVI"}}}], "num_of_checked_unique_partitions": 714, "hard_constraint_violations": {}}