{"number_of_cuts": 5, "elapsed_time": 3.17, "number_of_partitions_checked": 33649, "sel_partitions": [{"partition": [8, 16, 22, 28, 34], "ligation_fidelity": 0.99, "fragment_length_unevenness": 0.333, "cost": 116.2, "fusion_sites": ["AAAC", "AAGC", "AGGA", "ATGG", "CTGC"], "fragments": ["CMDWDSTN", "DRPKYFAS", "MFRRKG", "GFMDCG", "WLNRVC", "WEVNIE"], "expression": "\n[CMDWDS]AC<AAAC|>\n          <AAAC|>[DRPKYF]GC<AAGC|>\n                           <AAGC|>[MFRRK]GG<A|GGA>\n                                           <A|GGA>[FMDC]GG<A|TGG>\n                                                          <A|TGG>[LNR]GT<CTGC|>\n                                                                        <CTGC|>[WEVNIE]", "fragment_with_fusion_sites": {"CMDWDSTN": {"order": 0, "c_term_dna": "AC<AAAC|>", "middle_aa": "CMDWDS"}, "DRPKYFAS": {"order": 1, "n_term_dna": "<AAAC|>", "middle_aa": "DRPKYF", "c_term_dna": "GC<AAGC|>"}, "MFRRKG": {"order": 2, "n_term_dna": "<AAGC|>", "middle_aa": "MFRRK", "c_term_dna": "GG<A|GGA>"}, "GFMDCG": {"order": 3, "n_term_dna": "<A|GGA>", "middle_aa": "FMDC", "c_term_dna": "GG<A|TGG>"}, "WLNRVC": {"order": 4, "n_term_dna": "<A|TGG>", "middle_aa": "LNR", "c_term_dna": "GT<CTGC|>"}, "WEVNIE": {"order": 5, "n_term_dna": "<CTGC|>", "middle_aa": "WEVNIE"}}}, {"partition": [7, 16, 22, 28, 34], "ligation_fidelity": 0.99, "fragment_length_unevenness": 0.5, "cost": 116.2, "fusion_sites": ["AAAC", "AAGC", "AGGA", "ATGG", "CTGC"], "fragments": ["CMDWDST", "NDRPKYFAS", "MFRRKG", "GFMDCG", "WLNRVC", "WEVNIE"], "expression": "\n[CMDWDS]AC<A|AAC>\n          <A|AAC>[DRPKYF]GC<AAGC|>\n                           <AAGC|>[MFRRK]GG<A|GGA>\n                                           <A|GGA>[FMDC]GG<A|TGG>\n                                                          <A|TGG>[LNR]GT<CTGC|>\n                                                                        <CTGC|>[WEVNIE]", "fragment_with_fusion_sites": {"CMDWDST": {"order": 0, "c_term_dna": "AC<A|AAC>", "middle_aa": "CMDWDS"}, "NDRPKYFAS": {"order": 1, "n_term_dna": "<A|AAC>", "middle_aa": "DRPKYF", "c_term_dna": "GC<AAGC|>"}, "MFRRKG": {"order": 2, "n_term_dna": "<AAGC|>", "middle_aa": "MFRRK", "c_term_dna": "GG<A|GGA>"}, "GFMDCG": {"order": 3, "n_term_dna": "<A|GGA>", "middle_aa": "FMDC", "c_term_dna": "GG<A|TGG>"}, "WLNRVC": {"order": 4, "n_term_dna": "<A|TGG>", "middle_aa": "LNR", "c_term_dna": "GT<CTGC|>"}, "WEVNIE": {"order": 5, "n_term_dna": "<CTGC|>", "middle_aa": "WEVNIE"}}}, {"partition": [9, 16, 22, 28, 34], "ligation_fidelity": 0.99, "fragment_length_unevenness": 0.5, "cost": 116.2, "fusion_sites": ["ACAG", "AAGC", "AGGA", "ATGG", "GTGC"], "fragments": ["CMDWDSTND", "RPKYFAS", "MFRRKG", "GFMDCG", "WLNRVC", "WEVNIE"], "expression": "\n[CMDWDSTN]G<AC|AG>\n           <AC|AG>G[PKYF]GC<AAGC|>\n                           <AAGC|>[MFRRK]GG<A|GGA>\n                                           <A|GGA>[FMDC]GG<A|TGG>\n                                                          <A|TGG>[LNR]GT<GTGC|>\n                                                                        <GTGC|>[WEVNIE]", "fragment_with_fusion_sites": {"CMDWDSTND": {"order": 0, "c_term_dna": "G<AC|AG>", "middle_aa": "CMDWDSTN"}, "RPKYFAS": {"order": 1, "n_term_dna": "<AC|AG>G", "middle_aa": "PKYF", "c_term_dna": "GC<AAGC|>"}, "MFRRKG": {"order": 2, "n_term_dna": "<AAGC|>", "middle_aa": "MFRRK", "c_term_dna": "GG<A|GGA>"}, "GFMDCG": {"order": 3, "n_term_dna": "<A|GGA>", "middle_aa": "FMDC", "c_term_dna": "GG<A|TGG>"}, "WLNRVC": {"order": 4, "n_term_dna": "<A|TGG>", "middle_aa": "LNR", "c_term_dna": "GT<GTGC|>"}, "WEVNIE": {"order": 5, "n_term_dna": "<GTGC|>", "middle_aa": "WEVNIE"}}}], "num_of_checked_unique_partitions": 33649, "hard_constraint_violations": {"Fragment(s) too short.": 33606}}