{"s": "HIDIQMKETGYCPGNFHDWENYDEMLRWESKTECFKWSCSPAAAYGSVFAVGCHLMFLNANSSQSKGTGVKICLCRYQWVSPCGNDEYEYRLFWFKICLY", "mutations_0idx": [{"position": 7, "aa": ["W", "G", "M", "R"]}, {"position": 19, "aa": ["F", "Q", "L", "A"]}, {"position": 37, "aa": ["T", "C", "W", "Y"]}, {"position": 40, "aa": ["Y"]}, {"position": 45, "aa": ["D"]}, {"position": 52, "aa": ["W", "G", "M", "D"]}, {"position": 62, "aa": ["G"]}, {"position": 74, "aa": ["F"]}], "linked_mutations_0idx": null, "cut_number_range": [1, 5], "fidelity_data_path": "C:\\Users\\GOFKV\\PycharmProjects\\proseqteleporter\\proseqteleporter\\data\\neb_fidelity_data\\FileS01_T4_01h_25C.xlsx", "fusion_sites_used_by_backbone": ["CTTG", "TAAT"], "min_aa_length": 6, "provider_max_dna_length": 1500, "max_cost": 50000.0, "max_unevenness": 49.0, "min_ligation_fidelity": 0.98, "satisfaction_fidelity": 0.98, "output_dir": "C:\\Users\\GOFKV\\PycharmProjects\\proseqteleporter\\experiments\\assembly_cond\\input_assembly_cond_rep0\\T4_01h_25C_input_rep0_2024-06-25output", "supress_output": false, "search_method": "BFS", "codon_usage_tbl_dir": "C:\\Users\\GOFKV\\PycharmProjects\\proseqteleporter\\proseqteleporter\\data\\codon_usage", "host": "c_griseus", "sort_by_cost": true, "enzyme": "BsaI", "allowed_cut_positions_1idx": [], "partition_search_mode": "dist_mut_1", "select_top_n_partitions": 3}