{"number_of_cuts": 3, "elapsed_time": 18.67, "number_of_partitions_checked": 2346, "sel_partitions": [{"partition": [26, 52, 77], "ligation_fidelity": 1.0, "fragment_length_unevenness": 0.13, "cost": 810.0, "fusion_sites": ["AATG", "AAGC", "AAAA"], "fragments": ["RHQWLFFNGNYTATRRIKVNGVRRDQ", "MLTGVITLQFCGCNVPHCWHRLCVWI", "SHINCAWIIWASKNCIVVVICHNHK", "MSMITTCCMDMFMESGTNSPTHQ"], "expression": "\n[RHQWLFFNGNYTATRRIKVNGVRRD]CA<A|ATG>\n                             <A|ATG>[LTGVITLQFCGCNVPHCWHRLCVW]AT<A|AGC>\n                                                                <A|AGC>[HINCAWIIWASKNCIVVVICHNH]<AAA|A>\n                                                                                                <AAA|A>TG[SMITTCCMDMFMESGTNSPTHQ]", "fragment_with_fusion_sites": {"RHQWLFFNGNYTATRRIKVNGVRRDQ": {"order": 0, "c_term_dna": "CA<A|ATG>", "middle_aa": "RHQWLFFNGNYTATRRIKVNGVRRD"}, "MLTGVITLQFCGCNVPHCWHRLCVWI": {"order": 1, "n_term_dna": "<A|ATG>", "middle_aa": "LTGVITLQFCGCNVPHCWHRLCVW", "c_term_dna": "AT<A|AGC>"}, "SHINCAWIIWASKNCIVVVICHNHK": {"order": 2, "n_term_dna": "<A|AGC>", "middle_aa": "HINCAWIIWASKNCIVVVICHNH", "c_term_dna": "<AAA|A>"}, "MSMITTCCMDMFMESGTNSPTHQ": {"order": 3, "n_term_dna": "<AAA|A>TG", "middle_aa": "SMITTCCMDMFMESGTNSPTHQ"}}}, {"partition": [25, 52, 77], "ligation_fidelity": 1.0, "fragment_length_unevenness": 0.174, "cost": 810.0, "fusion_sites": ["ACCA", "AAGC", "AAAA"], "fragments": ["RHQWLFFNGNYTATRRIKVNGVRRD", "QMLTGVITLQFCGCNVPHCWHRLCVWI", "SHINCAWIIWASKNCIVVVICHNHK", "MSMITTCCMDMFMESGTNSPTHQ"], "expression": "\n[RHQWLFFNGNYTATRRIKVNGVRR]G<AC|CA>\n                           <AC|CA>G[MLTGVITLQFCGCNVPHCWHRLCVW]AT<A|AGC>\n                                                                <A|AGC>[HINCAWIIWASKNCIVVVICHNH]<AAA|A>\n                                                                                                <AAA|A>TG[SMITTCCMDMFMESGTNSPTHQ]", "fragment_with_fusion_sites": {"RHQWLFFNGNYTATRRIKVNGVRRD": {"order": 0, "c_term_dna": "G<AC|CA>", "middle_aa": "RHQWLFFNGNYTATRRIKVNGVRR"}, "QMLTGVITLQFCGCNVPHCWHRLCVWI": {"order": 1, "n_term_dna": "<AC|CA>G", "middle_aa": "MLTGVITLQFCGCNVPHCWHRLCVW", "c_term_dna": "AT<A|AGC>"}, "SHINCAWIIWASKNCIVVVICHNHK": {"order": 2, "n_term_dna": "<A|AGC>", "middle_aa": "HINCAWIIWASKNCIVVVICHNH", "c_term_dna": "<AAA|A>"}, "MSMITTCCMDMFMESGTNSPTHQ": {"order": 3, "n_term_dna": "<AAA|A>TG", "middle_aa": "SMITTCCMDMFMESGTNSPTHQ"}}}, {"partition": [26, 53, 77], "ligation_fidelity": 1.0, "fragment_length_unevenness": 0.174, "cost": 810.0, "fusion_sites": ["AATG", "AAGC", "AAAA"], "fragments": ["RHQWLFFNGNYTATRRIKVNGVRRDQ", "MLTGVITLQFCGCNVPHCWHRLCVWIS", "HINCAWIIWASKNCIVVVICHNHK", "MSMITTCCMDMFMESGTNSPTHQ"], "expression": "\n[RHQWLFFNGNYTATRRIKVNGVRRD]CA<A|ATG>\n                             <A|ATG>[LTGVITLQFCGCNVPHCWHRLCVW]AT<AAGC|>\n                                                                <AAGC|>[HINCAWIIWASKNCIVVVICHNH]<AAA|A>\n                                                                                                <AAA|A>TG[SMITTCCMDMFMESGTNSPTHQ]", "fragment_with_fusion_sites": {"RHQWLFFNGNYTATRRIKVNGVRRDQ": {"order": 0, "c_term_dna": "CA<A|ATG>", "middle_aa": "RHQWLFFNGNYTATRRIKVNGVRRD"}, "MLTGVITLQFCGCNVPHCWHRLCVWIS": {"order": 1, "n_term_dna": "<A|ATG>", "middle_aa": "LTGVITLQFCGCNVPHCWHRLCVW", "c_term_dna": "AT<AAGC|>"}, "HINCAWIIWASKNCIVVVICHNHK": {"order": 2, "n_term_dna": "<AAGC|>", "middle_aa": "HINCAWIIWASKNCIVVVICHNH", "c_term_dna": "<AAA|A>"}, "MSMITTCCMDMFMESGTNSPTHQ": {"order": 3, "n_term_dna": "<AAA|A>TG", "middle_aa": "SMITTCCMDMFMESGTNSPTHQ"}}}], "num_of_checked_unique_partitions": 2346, "hard_constraint_violations": {}}